{"trial_id": "0081", "hyperparameters": {"space": [{"class_name": "Int", "config": {"name": "units_1", "default": null, "conditions": [], "min_value": 16, "max_value": 512, "step": 16, "sampling": "linear"}}, {"class_name": "Int", "config": {"name": "units_2", "default": null, "conditions": [], "min_value": 16, "max_value": 512, "step": 16, "sampling": "linear"}}, {"class_name": "Int", "config": {"name": "units_3", "default": null, "conditions": [], "min_value": 16, "max_value": 512, "step": 16, "sampling": "linear"}}, {"class_name": "Float", "config": {"name": "learning_rate", "default": 0.05, "conditions": [], "min_value": 0.05, "max_value": 0.5, "step": null, "sampling": "linear"}}, {"class_name": "Float", "config": {"name": "dropout_rate", "default": 0.01, "conditions": [], "min_value": 0.01, "max_value": 0.8, "step": null, "sampling": "linear"}}, {"class_name": "Choice", "config": {"name": "optimizer", "default": "adam", "conditions": [], "values": ["adam", "rmsprop", "adagrad"], "ordered": false}}, {"class_name": "Choice", "config": {"name": "activation_1", "default": "relu", "conditions": [], "values": ["relu", "elu", "tanh", "sigmoid", "selu"], "ordered": false}}, {"class_name": "Choice", "config": {"name": "activation_2", "default": "relu", "conditions": [], "values": ["relu", "elu", "tanh", "sigmoid", "selu"], "ordered": false}}, {"class_name": "Choice", "config": {"name": "activation_3", "default": "relu", "conditions": [], "values": ["relu", "elu", "tanh", "sigmoid", "selu"], "ordered": false}}], "values": {"units_1": 16, "units_2": 32, "units_3": 496, "learning_rate": 0.4666677012396734, "dropout_rate": 0.6734530685308404, "optimizer": "rmsprop", "activation_1": "relu", "activation_2": "tanh", "activation_3": "tanh", "tuner/epochs": 10, "tuner/initial_epoch": 0, "tuner/bracket": 1, "tuner/round": 0}}, "metrics": {"metrics": {"loss": {"direction": "min", "observations": [{"value": [0.5852885842323303], "step": 3}]}, "binary_accuracy": {"direction": "max", "observations": [{"value": [0.730561375617981], "step": 3}]}, "precision": {"direction": "min", "observations": [{"value": [0.4278355538845062], "step": 3}]}, "recall": {"direction": "min", "observations": [{"value": [0.7273759245872498], "step": 3}]}, "val_loss": {"direction": "min", "observations": [{"value": [0.7683214545249939], "step": 3}]}, "val_binary_accuracy": {"direction": "max", "observations": [{"value": [0.6930526494979858], "step": 3}]}, "val_precision": {"direction": "max", "observations": [{"value": [0.3564620614051819], "step": 3}]}, "val_recall": {"direction": "min", "observations": [{"value": [0.43226999044418335], "step": 3}]}}}, "score": 0.3564620614051819, "best_step": 3, "status": "COMPLETED", "message": null}